MANIFEST.in
README.rst
setup.py
pylobby/__init__.py
pylobby/core.py
pylobby/exceptions.py
pylobby.egg-info/PKG-INFO
pylobby.egg-info/SOURCES.txt
pylobby.egg-info/dependency_links.txt
pylobby.egg-info/requires.txt
pylobby.egg-info/top_level.txt
pylobby/client/__init__.py
pylobby/server/__init__.py