Metadata-Version: 1.1
Name: pylobby
Version: 0.1.0
Summary: Distributed chat system
Home-page: https://github.com/dnaeon/pylobby
Author: Marin Atanasov Nikolov
Author-email: dnaeon@gmail.com
License: BSD
Download-URL: https://github.com/dnaeon/pylobby/releases
Platform: UNKNOWN
